LICENSE.txt
README.md
setup.py
src/emojipasta/__init__.py
src/emojipasta/__main__.py
src/emojipasta/bot.py
src/emojipasta/generator.py
src/emojipasta/data/__init__.py
src/emojipasta/data/emoji-mappings.json
src/emojipasta/data/emojipasta-comments.txt
src/emojipasta/scraping/__init__.py
src/emojipasta/scraping/parsing.py
src/emojipasta/scraping/reddit_scraping.py
src/emojipasta/util/__init__.py
src/emojipasta/util/cli.py
src/emojipasta/util/client.py
src/emojipasta/util/emoji.py
src/emojipasta/util/files.py
src/emojipasta/util/text.py
src/emojipasta_cli.egg-info/PKG-INFO
src/emojipasta_cli.egg-info/SOURCES.txt
src/emojipasta_cli.egg-info/dependency_links.txt
src/emojipasta_cli.egg-info/entry_points.txt
src/emojipasta_cli.egg-info/requires.txt
src/emojipasta_cli.egg-info/top_level.txt