Metadata-Version: 2.1
Name: emojipasta-cli
Version: 1.1.0
Summary: Generate emojipasta from text.
Home-page: https://github.com/MbBrainz/EmojipastaCLI
Author: Kevin Galligan
Author-email: galligankevinp@gmail.com
Classifier: Programming Language :: Python
Classifier: Programming Language :: Python :: 3
Classifier: License :: OSI Approved :: MIT License
Classifier: Operating System :: OS Independent
Classifier: Intended Audience :: Developers
Classifier: Topic :: Software Development :: Libraries :: Python Modules
License-File: LICENSE.txt
